LICENSE
MANIFEST.in
README.md
setup.py
version
lightStart/__init__.py
lightStart/__main__.py
lightStart/main.py
lightStart.egg-info/PKG-INFO
lightStart.egg-info/SOURCES.txt
lightStart.egg-info/dependency_links.txt
lightStart.egg-info/entry_points.txt
lightStart.egg-info/not-zip-safe
lightStart.egg-info/top_level.txt
lightStart/database/core.py
lightStart/database/exceptions.py
lightStart/database/templates/database.json
lightStart/database/templates/settings.json
lightStart/discord/build.py
lightStart/discord/client.py
lightStart/discord/gateway/argument_handler.py
lightStart/discord/gateway/codes.py
lightStart/discord/gateway/session.py
lightStart/utils/console.py
lightStart/utils/files.py
lightStart/utils/logger.py
lightStart/utils/merge.py
lightStart/utils/replace.py
lightStart/utils/requests.py
lightStart/utils/shared.py