Metadata-Version: 2.1
Name: lightStart
Version: 1.1.1b0
Summary: A fast, free, and open-source Dank Memer self-bot.
Home-page: https://github.com/splewdge/lightStart
Author: splewdge
Author-email: splewdge@proton.me
License: GNU AFFERO GENERAL PUBLIC LICENSE
Keywords: discord,self-bot,dank-memer,python,python3
Classifier: Development Status :: 4 - Beta
Classifier: Environment :: Console
Classifier: Intended Audience :: End Users/Desktop
Classifier: License :: OSI Approved :: GNU Affero General Public License v3
Classifier: Natural Language :: English
Classifier: Operating System :: OS Independent
Classifier: Programming Language :: Python :: 3 :: Only
Classifier: Topic :: Terminals
License-File: LICENSE
